libboost_headers
