Metadata-Version: 2.2
Name: libboost-headers
Version: 1.87.0
Summary: Repackaging of libboost-headers distributed via PyPI
Author-email: Contributors to the Power Grid Model project <powergridmodel@lfenergy.org>
License: BSL-1.0
Project-URL: Home-page, http://www.boost.org/
Project-URL: GitHub, https://github.com/boostorg/boost
Project-URL: Documentation, https://www.boost.org/doc/
Classifier: Programming Language :: C++
Classifier: Development Status :: 5 - Production/Stable
Classifier: Intended Audience :: Developers
Classifier: License :: OSI Approved :: Boost Software License 1.0 (BSL-1.0)
Classifier: Operating System :: Microsoft :: Windows
Classifier: Operating System :: POSIX :: Linux
Classifier: Operating System :: MacOS
Classifier: Topic :: File Formats
Classifier: Topic :: Software Development :: Libraries
License-File: LICENSE
Requires-Dist: importlib-resources
Provides-Extra: dev
Requires-Dist: pytest; extra == "dev"
